googleimagesearch/__init__.py
googleimagesearch-1.0.2.dist-info/DESCRIPTION.rst
googleimagesearch-1.0.2.dist-info/METADATA
googleimagesearch-1.0.2.dist-info/RECORD
googleimagesearch-1.0.2.dist-info/WHEEL
googleimagesearch-1.0.2.dist-info/metadata.json
googleimagesearch-1.0.2.dist-info/top_level.txt
