Metadata-Version: 2.0
Name: googleimagesearch
Version: 1.0.2
Summary: A simple API for using Google Image Search
Home-page: https://github.com/expenses/googleimagesearch
Author: expenses
Author-email: expenses@airmail.cc
License: MIT
Keywords: google image search
Platform: UNKNOWN
Requires-Dist: requests
